Dot-Dot-Dee/DotDotDee.py
Dot-Dot-Dee/__init__.py
tests/__init__.py
tests/test_dotdotdee.py
Dot_Dot_Dee-1.0.0.dist-info/METADATA
Dot_Dot_Dee-1.0.0.dist-info/WHEEL
Dot_Dot_Dee-1.0.0.dist-info/top_level.txt
Dot_Dot_Dee-1.0.0.dist-info/RECORD
